wjswgs/src/__init__.py
wjswgs/src/lasso.py
wjswgs/src/merge.py
wjswgs-0.1.0.dist-info/METADATA
wjswgs-0.1.0.dist-info/WHEEL
wjswgs-0.1.0.dist-info/top_level.txt
wjswgs-0.1.0.dist-info/RECORD
