Metadata-Version: 2.4
Name: wjswgs
Version: 0.1.0
Summary: A comprehensive machine learning pipeline toolkit for feature engineering and model training
Author-email: Your Name <your.email@example.com>
License: MIT
Keywords: machine-learning,pipeline,feature-engineering
Classifier: Development Status :: 4 - Beta
Classifier: License :: OSI Approved :: MIT License
Classifier: Programming Language :: Python :: 3.10
Requires-Python: >=3.10
